[
  {
    "name":"card1",
    "url":"static/resources/card1.png",
    "disposableContainers":
    {
      "melee":true,
      "distant":true,
      "enemyMelee":false,
      "enemyDistant":false
    },
    "power":8
  },
  {
    "name":"card2",
    "url":"static/resources/card2.png",
    "disposableContainers":
    {
      "melee":false,
      "distant":true,
      "enemyMelee":false,
      "enemyDistant":true
    },
    "power":8
  },
  {
    "name":"card3",
    "url":"static/resources/card3.png",
    "disposableContainers":
    {
      "melee":true,
      "distant":false,
      "enemyMelee":false,
      "enemyDistant":false
    },
    "power":8
  }
]